LICENSE
MANIFEST.in
README.md
setup.py
renus/__init__.py
renus/app.py
renus.egg-info/PKG-INFO
renus.egg-info/SOURCES.txt
renus.egg-info/dependency_links.txt
renus.egg-info/requires.txt
renus.egg-info/top_level.txt
renus/commands/__init__.py
renus/commands/help.py
renus/commands/run.py
renus/commands/app/__init__.py
renus/commands/app/controller.temp
renus/commands/app/model.temp
renus/commands/app/route.temp
renus/commands/app/run.py
renus/commands/app/vue.temp
renus/commands/backup/__init__.py
renus/commands/backup/run.py
renus/commands/copy/__init__.py
renus/commands/copy/run.py
renus/commands/default/__init__.py
renus/commands/default/run.py
renus/commands/extension/__init__.py
renus/commands/extension/build.py
renus/commands/extension/remove.py
renus/commands/extension/run.py
renus/commands/permission/__init__.py
renus/commands/permission/run.py
renus/core/__init__.py
renus/core/cache.py
renus/core/concurrency.py
renus/core/config.py
renus/core/cprint.py
renus/core/crypt.py
renus/core/datastructures.py
renus/core/exception.py
renus/core/formparsers.py
renus/core/injection.py
renus/core/log.py
renus/core/middleware.py
renus/core/model.py
renus/core/request.py
renus/core/response.py
renus/core/routing.py
renus/core/schedule.py
renus/core/serialize.py
renus/core/status.py
renus/core/websockets.py
renus/core/validation/__init__.py
renus/core/validation/rules.py
renus/core/validation/validate.py
renus/util/__init__.py
renus/util/helper.py