Metadata-Version: 2.1
Name: renus
Version: 2.5.0
Summary: Renus Core Framework
Home-page: https://github.com/smkoBa/renus
Author: Smko Bayazidi
Author-email: ba.smko@gmail.com
License: BSD
Requires-Python: >=3.8
License-File: LICENSE
Requires-Dist: anyio
Requires-Dist: python-multipart
Requires-Dist: pymongo
Requires-Dist: requests
Requires-Dist: setuptools
